{"cameraMode":{"drawMode":0,"name":"Shaded","section":"Shading Mode"},"sceneLighting":true,"audioPlay":false,"sceneViewState":{"showFog":true,"showMaterialUpdate":false,"showSkybox":true,"showFlares":true,"showImageEffects":true,"showParticleSystems":true},"in2DMode":false,"pivot":{"x":-102.056396484375,"y":-113.62002563476563,"z":-4.129960060119629},"rotation":{"x":0.1996486485004425,"y":0.0029395094607025387,"z":-0.0005989571800455451,"w":0.9798639416694641},"size":3.5863943099975588,"orthographic":false}